README.md
setup.py
samsgeneratechangelog/__init__.py
samsgeneratechangelog/__main__.py
samsgeneratechangelog/changelogfilehelper.py
samsgeneratechangelog/config.py
samsgeneratechangelog/decorators.py
samsgeneratechangelog/generatechangelog.py
samsgeneratechangelog/githelper.py
samsgeneratechangelog.egg-info/PKG-INFO
samsgeneratechangelog.egg-info/SOURCES.txt
samsgeneratechangelog.egg-info/dependency_links.txt
samsgeneratechangelog.egg-info/entry_points.txt
samsgeneratechangelog.egg-info/requires.txt
samsgeneratechangelog.egg-info/top_level.txt
samsgeneratechangelog/templates/author_all_commits.j2
samsgeneratechangelog/templates/author_by_change_type.j2
samsgeneratechangelog/templates/change_type_all_commits.j2
samsgeneratechangelog/templates/jira_id_all_commits.j2
samsgeneratechangelog/templates/jira_id_by_change_type.j2
samsgeneratechangelog/templates/root_folder_all_commits.j2