Metadata-Version: 2.1
Name: samsgeneratechangelog
Version: 1.0.2
Summary: Let Sam generate a changelog for you by grouping commits by file, or commit message, or anything!
Home-page: https://github.com/Sam-Martin/sams-generate-changelog
Author: Sam Martin
Author-email: samjackmartin+sams_generate_changelog@gmail.com
License: UNKNOWN
Project-URL: Documentation, https://sams-generate-changelog.readthedocs.io/en/latest/
Platform: UNKNOWN
Requires-Python: >=3.6.0
